easystruct.py
easystruct-0.1.2.dist-info/COPYING
easystruct-0.1.2.dist-info/WHEEL
easystruct-0.1.2.dist-info/METADATA
easystruct-0.1.2.dist-info/RECORD
